strainjedi/__init__.py
strainjedi/colors.py
strainjedi/jedi.py
strainjedi/quotes.py
strainjedi/io/__init__.py
strainjedi/io/gaussian.py
strainjedi/io/orca.py
strainjedi/io/qchem.py
strainjedi-1.0.0.dist-info/LICENSE
strainjedi-1.0.0.dist-info/LICENSE_old
strainjedi-1.0.0.dist-info/METADATA
strainjedi-1.0.0.dist-info/WHEEL
strainjedi-1.0.0.dist-info/top_level.txt
strainjedi-1.0.0.dist-info/RECORD
